londiste/__init__.py
londiste/admin.py
londiste/cli.py
londiste/compare.py
londiste/exec_attrs.py
londiste/handler.py
londiste/playback.py
londiste/repair.py
londiste/syncer.py
londiste/table_copy.py
londiste/util.py
londiste/handlers/__init__.py
londiste/handlers/applyfn.py
londiste/handlers/bulk.py
londiste/handlers/dispatch.py
londiste/handlers/multimaster.py
londiste/handlers/obfuscate.py
londiste/handlers/qtable.py
londiste/handlers/shard.py
londiste/handlers/vtable.py
londiste-3.12.dist-info/METADATA
londiste-3.12.dist-info/WHEEL
londiste-3.12.dist-info/entry_points.txt
londiste-3.12.dist-info/top_level.txt
londiste-3.12.dist-info/RECORD
